{
  "timestamp": "2026-06-10T20:07:44Z",
  "progress": 100,
  "services": {
    "phase2a": "ready",
    "phase2b": "ready",
    "phase2c": "ready"
  },
  "production": {
    "vercel": "REBUILDING",
    "vercel_http": "404",
    "vercel_status": "Root cause identified: vercel.json was deleted in commit c9347d7d. Recovery in progress: vercel.json restored @ 05:07 KST, pushed to main. Waiting for Vercel rebuild..."
  },
  "last_update": "2026-06-10 05:07:44",
  "critical_fix": {
    "issue": "vercel.json deleted during team-dashboard-p1 migration",
    "commit": "c9347d7d @ 2026-06-09 17:18:56 UTC",
    "recovery": "800e08c7 - vercel.json restored with original buildCommand & outputDirectory",
    "expected_recovery_time": "2026-06-10 05:15:00 (estimated)"
  }
}
