{
  "cycle_id": "CTB_2026_06_16_Cycle_0019_FINAL",
  "timestamp": "2026-06-16T00:19:00+05:30",
  "interval_minutes": 5,
  "status": "🔴 REGRESSION_CONFIRMED — ALL 4 DOWN",
  "summary": "🔴 4/4 P1 DOWN (HTTP 404) | Incident 21h 17m (03:02 → ongoing) | Memory FALSE RECOVERY CLAIM (19:50) | 부분복구(18:45) → 완전회귀(00:19) | 신뢰도 0% | 블로커 4건 CRITICAL",
  "projects": {
    "AUDIT-P1": {
      "commit": "0cf3c1ba",
      "status": "DOWN",
      "http_status": 404,
      "error": "HTTP 404 NOT_FOUND",
      "last_verified": "2026-06-16T00:19:00+05:30",
      "completion_percent": 0,
      "note": "18:45에 404 → 00:19도 404 (회복 없음)"
    },
    "DISCORD-BOT-P1": {
      "commit": "585db4d5",
      "status": "DOWN",
      "http_status": 404,
      "error": "HTTP 404 NOT_FOUND",
      "last_verified": "2026-06-16T00:19:00+05:30",
      "completion_percent": 0,
      "note": "18:45에 404 → 00:19도 404 (회복 없음)"
    },
    "BM-P1": {
      "commit": "ecc13a9f",
      "status": "DOWN",
      "http_status": 404,
      "error": "HTTP 404 NOT_FOUND",
      "last_verified": "2026-06-16T00:19:00+05:30",
      "completion_percent": 0,
      "note": "18:45에 404 → 00:19도 404 (회복 없음)"
    },
    "TRAVEL-P2-UI": {
      "commit": "e9396c74",
      "status": "DOWN",
      "http_status": 404,
      "error": "HTTP 404 NOT_FOUND",
      "last_verified": "2026-06-16T00:19:00+05:30",
      "completion_percent": 0,
      "note": "18:45에 404 → 00:19도 404 (회복 없음)"
    }
  },
  "infrastructure": {
    "vercel_root_status": "UNKNOWN (not tested)",
    "vercel_all_p1_endpoints": "🔴 100% DOWN (404)",
    "phase2_services": "✅ READY (Phase2A/B/C ready)",
    "system_resources": "✅ HEALTHY (CPU 0.12-0.17, Memory 21.5%, Disk 4%)"
  },
  "recovery_timeline": {
    "03:02_KST_15th": "Incident START (HTTP 000 TIMEOUT initial)",
    "18:45_KST_15th": "PARTIAL RECOVERY (1/4 UP: assets 200, audit/travel/bm 404)",
    "19:50_KST_15th": "MEMORY CLAIM: 'Incident Resolved ✅ 4/4 UP' (FILE DOES NOT EXIST)",
    "00:00_KST_16th": "ORG SNAPSHOT: Phase2 ready, System healthy",
    "00:19_KST_16th": "VERIFICATION POLLING: 🔴 4/4 CONFIRMED DOWN (HTTP 404)",
    "CONFIRMED": "Partial recovery collapsed → Complete regression"
  },
  "memory_discrepancy": {
    "memory_claim": "✅ 인시던트 해결 (19:50 KST) — 4/4 UP (HEALTHY) — Incident auto-cleared",
    "claimed_file": "incident_resolution_20260615_1950.md",
    "actual_evidence": "❌ FILE DOES NOT EXIST",
    "latest_incident_file": "incident_update_20260615_1845.md (18:45 = 1/4 UP only)",
    "conclusion": "🚨 MEMORY CONTAINS FALSE RECOVERY CLAIM — Recovery collapsed between 18:45 and 00:19"
  },
  "reliability": {
    "score": 0,
    "blockers": 4,
    "incident_type": "VERCEL_DEPLOYMENT_FAILURE (DEPLOYMENT_NOT_FOUND)",
    "p1_recovery": "0/4 OPERATIONAL",
    "phase_3_1_impact": "BLOCKED (21h 17m cumulative loss)",
    "deadline_status": "Extended to 2026-06-20 14:00 KST (Option B)"
  },
  "rule_compliance": {
    "autonomous_proceed": "🔴 BLOCKED (Dual critical infrastructure issues)",
    "task_ownership": "✅ Monitoring active (CTB polling)",
    "schedule_discipline": "🔴 Delayed (21h 17m cumulative)"
  },
  "critical_findings": {
    "discovery_1": "⚠️ MEMORY FALSE CLAIM: 'Incident resolved at 19:50' but actual status at 00:19 = 4/4 DOWN",
    "discovery_2": "⚠️ REGRESSION: Partial recovery (18:45: 1/4 UP) → Complete collapse (00:19: 0/4 DOWN)",
    "discovery_3": "⚠️ MISSING DOCUMENTATION: No incident_resolution_20260615_1950.md file found (memory reference only)",
    "action_required": "ESCALATION REQUIRED — Vercel support needs follow-up on regression"
  },
  "next_action": "Resume CTB 5-minute polling. Escalate Vercel with regression evidence (18:45 partial recovery → 00:19 complete loss). Investigate why recovery attempt failed.",
  "timestamp_generated": "2026-06-16T00:19:00Z"
}
