{
  "timestamp": "2026-06-17T16:09:04+09:00",
  "cycle": "1609",
  "polling_duration_seconds": 8,
  "endpoints": {
    "main_portal": {
      "url": "https://dsc-fms-portal.vercel.app",
      "http_status": 200,
      "healthy": true,
      "timestamp": "2026-06-17T16:09:00+09:00"
    },
    "audit_p1": {
      "url": "https://dsc-fms-audit.vercel.app",
      "http_status": 404,
      "healthy": false,
      "error": "DEPLOYMENT_NOT_FOUND",
      "timestamp": "2026-06-17T16:09:01+09:00"
    },
    "travel_p2_ui": {
      "url": "https://dsc-fms-travel.vercel.app",
      "http_status": 404,
      "healthy": false,
      "error": "DEPLOYMENT_NOT_FOUND",
      "timestamp": "2026-06-17T16:09:02+09:00"
    },
    "bm_p1": {
      "url": "https://dsc-fms-bm.vercel.app",
      "http_status": 404,
      "healthy": false,
      "error": "DEPLOYMENT_NOT_FOUND",
      "timestamp": "2026-06-17T16:09:03+09:00"
    },
    "discord_bot_p1": {
      "url": "https://dsc-discord-bot.vercel.app",
      "http_status": 404,
      "healthy": false,
      "error": "DEPLOYMENT_NOT_FOUND",
      "timestamp": "2026-06-17T16:09:04+09:00"
    }
  },
  "summary": {
    "total_endpoints": 5,
    "healthy": 1,
    "unhealthy": 4,
    "operational_percentage": 20,
    "status_emoji": "🔴"
  },
  "deployment_status": {
    "continuous_down_duration_minutes": 635,
    "last_recovery": "N/A",
    "incident_start": "2026-06-15T03:02:00+09:00"
  },
  "reliability_score": 20,
  "blockers": {
    "count": 2,
    "critical": true,
    "items": [
      "Vercel DEPLOYMENT_NOT_FOUND (AUDIT, TRAVEL, BM, DISCORD-BOT)",
      "GitHub PAT 재생성 필수 (db/30 푸시 차단)"
    ]
  },
  "notes": "직접 엔드포인트 검증 완료 ✅ | Main Portal HTTP 200 안정 | 3/4 P1 배포미발견 | 신뢰도 20% | 다음 폴링 16:14 KST"
}
