{
  "timestamp": "2026-06-14T18:30:01.642Z",
  "services": {
    "Phase2A": {
      "pid": 65516,
      "port": 3009,
      "rss": 64167936,
      "rssMB": 61,
      "vsz": 1062182912,
      "vszMB": 1013,
      "fds": 19
    },
    "Phase2B": {
      "pid": 65628,
      "port": 3010,
      "rss": 65196032,
      "rssMB": 62,
      "vsz": 1028640768,
      "vszMB": 981,
      "fds": 19
    },
    "Phase2C": {
      "pid": 65642,
      "port": 3011,
      "rss": 64843776,
      "rssMB": 62,
      "vsz": 1028366336,
      "vszMB": 981,
      "fds": 19
    }
  },
  "alerts": []
}